seekpath/__init__.py
seekpath/getpaths.py
seekpath/util.py
seekpath/brillouinzone/__init__.py
seekpath/brillouinzone/brillouinzone.py
seekpath/hpkot/__init__.py
seekpath/hpkot/spg_db.py
seekpath/hpkot/spg_mapping.py
seekpath/hpkot/tools.py
seekpath/hpkot/band_path_data/aP2/POSCAR_inversion
seekpath/hpkot/band_path_data/aP2/POSCAR_noinversion
seekpath/hpkot/band_path_data/aP2/k_vector_parameters.txt
seekpath/hpkot/band_path_data/aP2/path.txt
seekpath/hpkot/band_path_data/aP2/points.txt
seekpath/hpkot/band_path_data/aP3/POSCAR_inversion
seekpath/hpkot/band_path_data/aP3/POSCAR_noinversion
seekpath/hpkot/band_path_data/aP3/k_vector_parameters.txt
seekpath/hpkot/band_path_data/aP3/path.txt
seekpath/hpkot/band_path_data/aP3/points.txt
seekpath/hpkot/band_path_data/cF1/POSCAR_inversion
seekpath/hpkot/band_path_data/cF1/POSCAR_noinversion
seekpath/hpkot/band_path_data/cF1/k_vector_parameters.txt
seekpath/hpkot/band_path_data/cF1/path.txt
seekpath/hpkot/band_path_data/cF1/points.txt
seekpath/hpkot/band_path_data/cF2/POSCAR_inversion
seekpath/hpkot/band_path_data/cF2/POSCAR_noinversion
seekpath/hpkot/band_path_data/cF2/k_vector_parameters.txt
seekpath/hpkot/band_path_data/cF2/path.txt
seekpath/hpkot/band_path_data/cF2/points.txt
seekpath/hpkot/band_path_data/cI1/POSCAR_inversion
seekpath/hpkot/band_path_data/cI1/POSCAR_noinversion
seekpath/hpkot/band_path_data/cI1/k_vector_parameters.txt
seekpath/hpkot/band_path_data/cI1/path.txt
seekpath/hpkot/band_path_data/cI1/points.txt
seekpath/hpkot/band_path_data/cP1/POSCAR_inversion
seekpath/hpkot/band_path_data/cP1/POSCAR_noinversion
seekpath/hpkot/band_path_data/cP1/k_vector_parameters.txt
seekpath/hpkot/band_path_data/cP1/path.txt
seekpath/hpkot/band_path_data/cP1/points.txt
seekpath/hpkot/band_path_data/cP2/POSCAR_inversion
seekpath/hpkot/band_path_data/cP2/POSCAR_noinversion
seekpath/hpkot/band_path_data/cP2/k_vector_parameters.txt
seekpath/hpkot/band_path_data/cP2/path.txt
seekpath/hpkot/band_path_data/cP2/points.txt
seekpath-2.2.1.dist-info/licenses/LICENSE.txt
seekpath-2.2.1.dist-info/WHEEL
seekpath-2.2.1.dist-info/METADATA
seekpath-2.2.1.dist-info/RECORD
